{
  "generated_at": "2026-03-04 18:25",
  "sport": "NCAAB",
  "model_version": "v1.0",
  "ratings_source": "KenPom + Bart Torvik (35/65 blend)",
  "odds_api_remaining": 468,
  "parameters": {
    "kp_weight": 0.35,
    "bt_weight": 0.65,
    "default_hca": 2.5,
    "high_edge_threshold": 5.0,
    "medium_edge_threshold": 2.5
  },
  "summary": {
    "total_games": 40,
    "high_confidence": 1,
    "medium_confidence": 8,
    "no_edge": 22,
    "no_odds": 9
  },
  "predictions": [
    {
      "home_team": "South Carolina",
      "away_team": "Gardner Webb",
      "home_abbrev": "UPST",
      "away_abbrev": "GWEB",
      "date": "2026-03-04",
      "commence": "2026-03-05T00:30:00Z",
      "neutral_site": true,
      "model_spread": -23.3,
      "game_possessions": 67.9,
      "home_tt": 87.9,
      "away_tt": 64.6,
      "game_total": 152.5,
      "hca": 0,
      "home_bem": 6.89,
      "away_bem": -27.45,
      "home_boe": 112.21,
      "away_boe": 95.86,
      "home_bde": 105.32,
      "away_bde": 123.31,
      "home_bap": 66.2,
      "away_bap": 69.6,
      "home_conf": "SEC",
      "away_conf": "BSth",
      "kp_spread": null,
      "kp_total": null,
      "kp_home_score": null,
      "kp_away_score": null,
      "kp_home_wp": null,
      "kp_pred_tempo": null,
      "home_efg": 50.3448,
      "away_efg": 48.1505,
      "home_defg": 51.2941,
      "away_defg": 57.3639,
      "vegas_spread": -10.5,
      "consensus_spread": -10.5,
      "vegas_total": 144.16666666666666,
      "spread_book": "DraftKings",
      "books_count": 3,
      "edge": 12.8,
      "confidence": "HIGH",
      "recommendation": "BET South Carolina -10.5",
      "bet_team": "South Carolina",
      "bet_spread": -10.5
    },
    {
      "home_team": "La Salle",
      "away_team": "Fordham",
      "home_abbrev": "LAS",
      "away_abbrev": "FOR",
      "date": "2026-03-04",
      "commence": "2026-03-04T23:30:00Z",
      "neutral_site": false,
      "model_spread": -0.4,
      "game_possessions": 64.4,
      "home_tt": 67.8,
      "away_tt": 67.3,
      "game_total": 135.1,
      "hca": 2.6,
      "home_bem": -3.87,
      "away_bem": -0.52,
      "home_boe": 103.53,
      "away_boe": 103.52,
      "home_bde": 107.4,
      "away_bde": 104.04,
      "home_bap": 65.0,
      "away_bap": 63.8,
      "home_conf": "A10",
      "away_conf": "A10",
      "kp_spread": -1.0,
      "kp_total": 127.0,
      "kp_home_score": 64.0,
      "kp_away_score": 63.0,
      "kp_home_wp": 50.0,
      "kp_pred_tempo": 63.0,
      "home_efg": 45.0704,
      "away_efg": 48.3903,
      "home_defg": 54.4155,
      "away_defg": 50.0349,
      "vegas_spread": 3.5,
      "consensus_spread": 3.5,
      "vegas_total": 132.0,
      "spread_book": "BetMGM",
      "books_count": 2,
      "edge": 3.9,
      "confidence": "MEDIUM",
      "recommendation": "BET La Salle +3.5",
      "bet_team": "La Salle",
      "bet_spread": 3.5
    },
    {
      "home_team": "Detroit Mercy",
      "away_team": "Milwaukee",
      "home_abbrev": "DETM",
      "away_abbrev": "MILW",
      "date": "2026-03-04",
      "commence": "2026-03-05T00:00:00Z",
      "neutral_site": false,
      "model_spread": -5.4,
      "game_possessions": 68.2,
      "home_tt": 78.6,
      "away_tt": 73.2,
      "game_total": 151.8,
      "hca": 2.6,
      "home_bem": -4.16,
      "away_bem": -8.26,
      "home_boe": 109.08,
      "away_boe": 106.58,
      "home_bde": 113.23,
      "away_bde": 114.84,
      "home_bap": 69.0,
      "away_bap": 67.4,
      "home_conf": "Horz",
      "away_conf": "Horz",
      "kp_spread": -5.0,
      "kp_total": 155.0,
      "kp_home_score": 80.0,
      "kp_away_score": 75.0,
      "kp_home_wp": 66.0,
      "kp_pred_tempo": 69.0,
      "home_efg": 49.639,
      "away_efg": 50.1631,
      "home_defg": 52.9575,
      "away_defg": 55.3612,
      "vegas_spread": -1.5,
      "consensus_spread": -1.5,
      "vegas_total": 151.5,
      "spread_book": "DraftKings",
      "books_count": 3,
      "edge": 3.9,
      "confidence": "MEDIUM",
      "recommendation": "BET Detroit Mercy -1.5",
      "bet_team": "Detroit Mercy",
      "bet_spread": -1.5
    },
    {
      "home_team": "Georgia Southern",
      "away_team": "Old Dominion",
      "home_abbrev": "GASO",
      "away_abbrev": "ODU",
      "date": "2026-03-04",
      "commence": "2026-03-05T01:30:00Z",
      "neutral_site": true,
      "model_spread": 1.4,
      "game_possessions": 69.7,
      "home_tt": 76.4,
      "away_tt": 77.8,
      "game_total": 154.2,
      "hca": 0,
      "home_bem": -8.18,
      "away_bem": -6.22,
      "home_boe": 107.49,
      "away_boe": 106.1,
      "home_bde": 115.67,
      "away_bde": 112.32,
      "home_bap": 70.6,
      "away_bap": 68.9,
      "home_conf": "SB",
      "away_conf": "SB",
      "kp_spread": 2.0,
      "kp_total": 160.0,
      "kp_home_score": 79.0,
      "kp_away_score": 81.0,
      "kp_home_wp": 46.0,
      "kp_pred_tempo": 71.0,
      "home_efg": 50.0,
      "away_efg": 50.4854,
      "home_defg": 52.052,
      "away_defg": 50.461,
      "vegas_spread": -2.5,
      "consensus_spread": -2.5,
      "vegas_total": 157.5,
      "spread_book": "DraftKings",
      "books_count": 3,
      "edge": 3.9,
      "confidence": "MEDIUM",
      "recommendation": "BET Old Dominion +2.5",
      "bet_team": "Old Dominion",
      "bet_spread": 2.5
    },
    {
      "home_team": "Mercyhurst",
      "away_team": "Fairleigh Dickinson",
      "home_abbrev": "MERC",
      "away_abbrev": "FDU",
      "date": "2026-03-04",
      "commence": "2026-03-05T00:00:00Z",
      "neutral_site": false,
      "model_spread": -7.2,
      "game_possessions": 64.0,
      "home_tt": 73.4,
      "away_tt": 66.2,
      "game_total": 139.6,
      "hca": 2.5,
      "home_bem": -10.31,
      "away_bem": -17.64,
      "home_boe": 101.99,
      "away_boe": 101.15,
      "home_bde": 112.3,
      "away_bde": 118.8,
      "home_bap": 64.2,
      "away_bap": 63.7,
      "home_conf": "NEC",
      "away_conf": "NEC",
      "kp_spread": -7.0,
      "kp_total": 133.0,
      "kp_home_score": 70.0,
      "kp_away_score": 63.0,
      "kp_home_wp": 73.0,
      "kp_pred_tempo": 62.0,
      "home_efg": 49.4668,
      "away_efg": 47.2686,
      "home_defg": 50.4235,
      "away_defg": 55.1068,
      "vegas_spread": -3.5,
      "consensus_spread": -3.5,
      "vegas_total": 131.83333333333334,
      "spread_book": "DraftKings",
      "books_count": 3,
      "edge": 3.7,
      "confidence": "MEDIUM",
      "recommendation": "BET Mercyhurst -3.5",
      "bet_team": "Mercyhurst",
      "bet_spread": -3.5
    },
    {
      "home_team": "DePaul",
      "away_team": "Villanova",
      "home_abbrev": "DEP",
      "away_abbrev": "VILL",
      "date": "2026-03-04",
      "commence": "2026-03-05T01:00:00Z",
      "neutral_site": false,
      "model_spread": 5.0,
      "game_possessions": 65.2,
      "home_tt": 68.0,
      "away_tt": 73.0,
      "game_total": 141.0,
      "hca": 2.5,
      "home_bem": 7.95,
      "away_bem": 19.46,
      "home_boe": 108.3,
      "away_boe": 119.99,
      "home_bde": 100.36,
      "away_bde": 100.53,
      "home_bap": 65.9,
      "away_bap": 64.5,
      "home_conf": "BE",
      "away_conf": "BE",
      "kp_spread": 5.0,
      "kp_total": 135.0,
      "kp_home_score": 65.0,
      "kp_away_score": 70.0,
      "kp_home_wp": 34.0,
      "kp_pred_tempo": 64.0,
      "home_efg": 50.5814,
      "away_efg": 53.6663,
      "home_defg": 49.5932,
      "away_defg": 51.3546,
      "vegas_spread": 1.5,
      "consensus_spread": 1.8,
      "vegas_total": 135.5,
      "spread_book": "DraftKings",
      "books_count": 3,
      "edge": 3.5,
      "confidence": "MEDIUM",
      "recommendation": "BET Villanova -1.5",
      "bet_team": "Villanova",
      "bet_spread": -1.5
    },
    {
      "home_team": "Georgia Tech",
      "away_team": "California",
      "home_abbrev": "GT",
      "away_abbrev": "CAL",
      "date": "2026-03-04",
      "commence": "2026-03-05T00:00:00Z",
      "neutral_site": false,
      "model_spread": 5.9,
      "game_possessions": 69.1,
      "home_tt": 72.3,
      "away_tt": 78.1,
      "game_total": 150.4,
      "hca": 2.6,
      "home_bem": -0.3,
      "away_bem": 11.94,
      "home_boe": 107.16,
      "away_boe": 114.14,
      "home_bde": 107.45,
      "away_bde": 102.2,
      "home_bap": 70.6,
      "away_bap": 67.5,
      "home_conf": "ACC",
      "away_conf": "ACC",
      "kp_spread": 6.0,
      "kp_total": 150.0,
      "kp_home_score": 72.0,
      "kp_away_score": 78.0,
      "kp_home_wp": 31.0,
      "kp_pred_tempo": 70.0,
      "home_efg": 49.9714,
      "away_efg": 52.4443,
      "home_defg": 49.9172,
      "away_defg": 49.1612,
      "vegas_spread": 2.5,
      "consensus_spread": 2.2,
      "vegas_total": 155.16666666666666,
      "spread_book": "DraftKings",
      "books_count": 3,
      "edge": 3.4,
      "confidence": "MEDIUM",
      "recommendation": "BET California -2.5",
      "bet_team": "California",
      "bet_spread": -2.5
    },
    {
      "home_team": "Northwestern",
      "away_team": "Purdue",
      "home_abbrev": "NU",
      "away_abbrev": "PUR",
      "date": "2026-03-04",
      "commence": "2026-03-05T01:30:00Z",
      "neutral_site": false,
      "model_spread": 9.7,
      "game_possessions": 65.4,
      "home_tt": 69.5,
      "away_tt": 79.3,
      "game_total": 148.8,
      "hca": 2.6,
      "home_bem": 12.12,
      "away_bem": 30.92,
      "home_boe": 115.89,
      "away_boe": 130.35,
      "home_bde": 103.77,
      "away_bde": 99.44,
      "home_bap": 65.7,
      "away_bap": 65.0,
      "home_conf": "B10",
      "away_conf": "B10",
      "kp_spread": 9.0,
      "kp_total": 149.0,
      "kp_home_score": 70.0,
      "kp_away_score": 79.0,
      "kp_home_wp": 21.0,
      "kp_pred_tempo": 64.0,
      "home_efg": 51.1384,
      "away_efg": 57.7517,
      "home_defg": 49.9701,
      "away_defg": 51.4741,
      "vegas_spread": 12.5,
      "consensus_spread": 11.5,
      "vegas_total": 145.5,
      "spread_book": "DraftKings",
      "books_count": 3,
      "edge": 2.8,
      "confidence": "MEDIUM",
      "recommendation": "BET Northwestern +12.5",
      "bet_team": "Northwestern",
      "bet_spread": 12.5
    },
    {
      "home_team": "Providence",
      "away_team": "Marquette",
      "home_abbrev": "PROV",
      "away_abbrev": "MARQ",
      "date": "2026-03-04",
      "commence": "2026-03-05T00:00:00Z",
      "neutral_site": false,
      "model_spread": -6.2,
      "game_possessions": 70.0,
      "home_tt": 81.9,
      "away_tt": 75.7,
      "game_total": 157.6,
      "hca": 2.5,
      "home_bem": 13.28,
      "away_bem": 8.06,
      "home_boe": 123.13,
      "away_boe": 111.72,
      "home_bde": 109.85,
      "away_bde": 103.66,
      "home_bap": 71.1,
      "away_bap": 68.8,
      "home_conf": "BE",
      "away_conf": "BE",
      "kp_spread": -7.0,
      "kp_total": 165.0,
      "kp_home_score": 86.0,
      "kp_away_score": 79.0,
      "kp_home_wp": 74.0,
      "kp_pred_tempo": 72.0,
      "home_efg": 55.2428,
      "away_efg": 50.2817,
      "home_defg": 51.3695,
      "away_defg": 51.1403,
      "vegas_spread": -3.5,
      "consensus_spread": -3.8,
      "vegas_total": 161.5,
      "spread_book": "DraftKings",
      "books_count": 3,
      "edge": 2.7,
      "confidence": "MEDIUM",
      "recommendation": "BET Providence -3.5",
      "bet_team": "Providence",
      "bet_spread": -3.5
    },
    {
      "home_team": "SIUE",
      "away_team": "Eastern Illinois",
      "home_abbrev": "SIUE",
      "away_abbrev": "EIU",
      "date": "2026-03-04",
      "commence": "2026-03-05T00:00:00Z",
      "neutral_site": true,
      "model_spread": -6.0,
      "game_possessions": 64.9,
      "home_tt": 70.3,
      "away_tt": 64.3,
      "game_total": 134.6,
      "hca": 0,
      "home_bem": -6.83,
      "away_bem": -16.05,
      "home_boe": 99.03,
      "away_boe": 95.58,
      "home_bde": 105.86,
      "away_bde": 111.62,
      "home_bap": 64.3,
      "away_bap": 65.6,
      "home_conf": "OVC",
      "away_conf": "OVC",
      "kp_spread": -5.0,
      "kp_total": 123.0,
      "kp_home_score": 64.0,
      "kp_away_score": 59.0,
      "kp_home_wp": 69.0,
      "kp_pred_tempo": 63.0,
      "home_efg": 49.5889,
      "away_efg": 45.1966,
      "home_defg": 45.3233,
      "away_defg": 51.1104,
      "vegas_spread": -3.5,
      "consensus_spread": -3.8,
      "vegas_total": 128.16666666666666,
      "spread_book": "DraftKings",
      "books_count": 3,
      "edge": 2.5,
      "confidence": "NO_EDGE",
      "recommendation": "No edge",
      "bet_team": "SIUE",
      "bet_spread": -3.5
    },
    {
      "home_team": "Eastern Kentucky",
      "away_team": "Stetson",
      "home_abbrev": "EKU",
      "away_abbrev": "STET",
      "date": "2026-03-04",
      "commence": "2026-03-04T22:00:00Z",
      "neutral_site": true,
      "model_spread": -2.2,
      "game_possessions": 67.0,
      "home_tt": 76.9,
      "away_tt": 74.7,
      "game_total": 151.6,
      "hca": 0,
      "home_bem": -10.76,
      "away_bem": -13.98,
      "home_boe": 109.06,
      "away_boe": 104.39,
      "home_bde": 119.82,
      "away_bde": 118.37,
      "home_bap": 67.1,
      "away_bap": 66.8,
      "home_conf": "ASun",
      "away_conf": "ASun",
      "kp_spread": -2.0,
      "kp_total": 156.0,
      "kp_home_score": 79.0,
      "kp_away_score": 77.0,
      "kp_home_wp": 58.0,
      "kp_pred_tempo": 67.0,
      "home_efg": 51.8487,
      "away_efg": 52.8121,
      "home_defg": 55.8051,
      "away_defg": 55.3368,
      "vegas_spread": -4.5,
      "consensus_spread": -4.5,
      "vegas_total": 155.5,
      "spread_book": "FanDuel",
      "books_count": 3,
      "edge": 2.3,
      "confidence": "NO_EDGE",
      "recommendation": "No edge",
      "bet_team": "Stetson",
      "bet_spread": 4.5,
      "_locked": true
    },
    {
      "home_team": "Charlotte",
      "away_team": "UAB",
      "home_abbrev": "CLT",
      "away_abbrev": "UAB",
      "date": "2026-03-04",
      "commence": "2026-03-05T00:00:00Z",
      "neutral_site": false,
      "model_spread": 0.2,
      "game_possessions": 66.2,
      "home_tt": 72.9,
      "away_tt": 73.0,
      "game_total": 145.9,
      "hca": 2.7,
      "home_bem": -0.87,
      "away_bem": 3.41,
      "home_boe": 112.83,
      "away_boe": 108.23,
      "home_bde": 113.7,
      "away_bde": 104.82,
      "home_bap": 63.4,
      "away_bap": 68.9,
      "home_conf": "Amer",
      "away_conf": "Amer",
      "kp_spread": 1.0,
      "kp_total": 147.0,
      "kp_home_score": 73.0,
      "kp_away_score": 74.0,
      "kp_home_wp": 50.0,
      "kp_pred_tempo": 65.0,
      "home_efg": 53.688,
      "away_efg": 47.9015,
      "home_defg": 51.2539,
      "away_defg": 49.5357,
      "vegas_spread": 2.5,
      "consensus_spread": 2.5,
      "vegas_total": 146.83333333333334,
      "spread_book": "DraftKings",
      "books_count": 3,
      "edge": 2.3,
      "confidence": "NO_EDGE",
      "recommendation": "No edge",
      "bet_team": "Charlotte",
      "bet_spread": 2.5
    },
    {
      "home_team": "Penn St.",
      "away_team": "Ohio St.",
      "home_abbrev": "PSU",
      "away_abbrev": "OSU",
      "date": "2026-03-04",
      "commence": "2026-03-05T00:30:00Z",
      "neutral_site": false,
      "model_spread": 8.7,
      "game_possessions": 66.7,
      "home_tt": 72.3,
      "away_tt": 81.0,
      "game_total": 153.4,
      "hca": 2.6,
      "home_bem": 3.85,
      "away_bem": 20.71,
      "home_boe": 115.73,
      "away_boe": 123.56,
      "home_bde": 111.89,
      "away_bde": 102.85,
      "home_bap": 67.3,
      "away_bap": 66.1,
      "home_conf": "B10",
      "away_conf": "B10",
      "kp_spread": 8.0,
      "kp_total": 156.0,
      "kp_home_score": 74.0,
      "kp_away_score": 82.0,
      "kp_home_wp": 25.0,
      "kp_pred_tempo": 66.0,
      "home_efg": 53.307,
      "away_efg": 55.5623,
      "home_defg": 58.0896,
      "away_defg": 49.8825,
      "vegas_spread": 6.5,
      "consensus_spread": 7.0,
      "vegas_total": 152.5,
      "spread_book": "DraftKings",
      "books_count": 2,
      "edge": 2.2,
      "confidence": "NO_EDGE",
      "recommendation": "No edge",
      "bet_team": "Ohio St.",
      "bet_spread": -6.5
    },
    {
      "home_team": "Oakland",
      "away_team": "Northern Kentucky",
      "home_abbrev": "OAK",
      "away_abbrev": "NKU",
      "date": "2026-03-04",
      "commence": "2026-03-05T00:00:00Z",
      "neutral_site": false,
      "model_spread": -3.5,
      "game_possessions": 69.7,
      "home_tt": 79.6,
      "away_tt": 76.1,
      "game_total": 155.7,
      "hca": 2.6,
      "home_bem": -0.33,
      "away_bem": -1.57,
      "home_boe": 114.56,
      "away_boe": 107.72,
      "home_bde": 114.89,
      "away_bde": 109.29,
      "home_bap": 69.8,
      "away_bap": 69.6,
      "home_conf": "Horz",
      "away_conf": "Horz",
      "kp_spread": -4.0,
      "kp_total": 164.0,
      "kp_home_score": 84.0,
      "kp_away_score": 80.0,
      "kp_home_wp": 62.0,
      "kp_pred_tempo": 71.0,
      "home_efg": 52.7854,
      "away_efg": 52.9343,
      "home_defg": 54.7035,
      "away_defg": 54.0457,
      "vegas_spread": -1.5,
      "consensus_spread": -1.5,
      "vegas_total": 162.16666666666666,
      "spread_book": "DraftKings",
      "books_count": 3,
      "edge": 2.0,
      "confidence": "NO_EDGE",
      "recommendation": "No edge",
      "bet_team": "Oakland",
      "bet_spread": -1.5
    },
    {
      "home_team": "James Madison",
      "away_team": "Louisiana",
      "home_abbrev": "JMU",
      "away_abbrev": "UL",
      "date": "2026-03-04",
      "commence": "2026-03-04T23:00:00Z",
      "neutral_site": true,
      "model_spread": -4.7,
      "game_possessions": 64.0,
      "home_tt": 72.4,
      "away_tt": 67.7,
      "game_total": 140.1,
      "hca": 0,
      "home_bem": -3.7,
      "away_bem": -10.96,
      "home_boe": 108.9,
      "away_boe": 101.53,
      "home_bde": 112.6,
      "away_bde": 112.49,
      "home_bap": 65.3,
      "away_bap": 62.8,
      "home_conf": "SB",
      "away_conf": "SB",
      "kp_spread": -5.0,
      "kp_total": 135.0,
      "kp_home_score": 70.0,
      "kp_away_score": 65.0,
      "kp_home_wp": 69.0,
      "kp_pred_tempo": 62.0,
      "home_efg": 52.7859,
      "away_efg": 47.1799,
      "home_defg": 49.0555,
      "away_defg": 52.3342,
      "vegas_spread": -6.5,
      "consensus_spread": -6.2,
      "vegas_total": 132.83333333333334,
      "spread_book": "DraftKings",
      "books_count": 3,
      "edge": 1.8,
      "confidence": "NO_EDGE",
      "recommendation": "No edge",
      "bet_team": "Louisiana",
      "bet_spread": 6.5,
      "_locked": true
    },
    {
      "home_team": "Le Moyne",
      "away_team": "Stonehill",
      "home_abbrev": "LEM",
      "away_abbrev": "STO",
      "date": "2026-03-04",
      "commence": "2026-03-05T00:00:00Z",
      "neutral_site": false,
      "model_spread": -6.4,
      "game_possessions": 67.7,
      "home_tt": 73.8,
      "away_tt": 67.4,
      "game_total": 141.2,
      "hca": 2.4,
      "home_bem": -11.43,
      "away_bem": -17.38,
      "home_boe": 101.16,
      "away_boe": 91.96,
      "home_bde": 112.59,
      "away_bde": 109.34,
      "home_bap": 69.3,
      "away_bap": 66.1,
      "home_conf": "NEC",
      "away_conf": "NEC",
      "kp_spread": -7.0,
      "kp_total": 135.0,
      "kp_home_score": 71.0,
      "kp_away_score": 64.0,
      "kp_home_wp": 74.0,
      "kp_pred_tempo": 68.0,
      "home_efg": 53.005,
      "away_efg": 46.9166,
      "home_defg": 49.1131,
      "away_defg": 48.2122,
      "vegas_spread": -4.5,
      "consensus_spread": -4.5,
      "vegas_total": 140.0,
      "spread_book": "BetMGM",
      "books_count": 2,
      "edge": 1.9,
      "confidence": "NO_EDGE",
      "recommendation": "No edge",
      "bet_team": "Le Moyne",
      "bet_spread": -4.5
    },
    {
      "home_team": "Rhode Island",
      "away_team": "Duquesne",
      "home_abbrev": "URI",
      "away_abbrev": "DUQ",
      "date": "2026-03-04",
      "commence": "2026-03-05T00:00:00Z",
      "neutral_site": false,
      "model_spread": -0.8,
      "game_possessions": 67.6,
      "home_tt": 73.1,
      "away_tt": 72.3,
      "game_total": 145.3,
      "hca": 2.6,
      "home_bem": 1.7,
      "away_bem": 4.42,
      "home_boe": 106.21,
      "away_boe": 111.38,
      "home_bde": 104.52,
      "away_bde": 106.95,
      "home_bap": 65.9,
      "away_bap": 69.3,
      "home_conf": "A10",
      "away_conf": "A10",
      "kp_spread": -2.0,
      "kp_total": 144.0,
      "kp_home_score": 73.0,
      "kp_away_score": 71.0,
      "kp_home_wp": 58.0,
      "kp_pred_tempo": 68.0,
      "home_efg": 50.3145,
      "away_efg": 53.2974,
      "home_defg": 51.1566,
      "away_defg": 51.8041,
      "vegas_spread": -2.5,
      "consensus_spread": -2.5,
      "vegas_total": 143.5,
      "spread_book": "DraftKings",
      "books_count": 3,
      "edge": 1.7,
      "confidence": "NO_EDGE",
      "recommendation": "No edge",
      "bet_team": "Duquesne",
      "bet_spread": 2.5
    },
    {
      "home_team": "Notre Dame",
      "away_team": "Stanford",
      "home_abbrev": "ND",
      "away_abbrev": "STAN",
      "date": "2026-03-04",
      "commence": "2026-03-05T02:00:00Z",
      "neutral_site": false,
      "model_spread": -0.0,
      "game_possessions": 66.3,
      "home_tt": 73.3,
      "away_tt": 73.3,
      "game_total": 146.6,
      "hca": 2.6,
      "home_bem": 8.67,
      "away_bem": 12.59,
      "home_boe": 115.29,
      "away_boe": 115.86,
      "home_bde": 106.63,
      "away_bde": 103.27,
      "home_bap": 65.5,
      "away_bap": 67.0,
      "home_conf": "ACC",
      "away_conf": "ACC",
      "kp_spread": -1.0,
      "kp_total": 145.0,
      "kp_home_score": 73.0,
      "kp_away_score": 72.0,
      "kp_home_wp": 53.0,
      "kp_pred_tempo": 65.0,
      "home_efg": 52.5801,
      "away_efg": 50.8524,
      "home_defg": 51.583,
      "away_defg": 51.2975,
      "vegas_spread": 1.5,
      "consensus_spread": 1.5,
      "vegas_total": 147.83333333333334,
      "spread_book": "DraftKings",
      "books_count": 3,
      "edge": 1.5,
      "confidence": "NO_EDGE",
      "recommendation": "No edge",
      "bet_team": "Notre Dame",
      "bet_spread": 1.5
    },
    {
      "home_team": "Washington",
      "away_team": "USC",
      "home_abbrev": "WASH",
      "away_abbrev": "USC",
      "date": "2026-03-04",
      "commence": "2026-03-05T03:30:00Z",
      "neutral_site": false,
      "model_spread": -4.3,
      "game_possessions": 68.6,
      "home_tt": 76.5,
      "away_tt": 72.2,
      "game_total": 148.7,
      "hca": 2.5,
      "home_bem": 15.1,
      "away_bem": 12.62,
      "home_boe": 116.49,
      "away_boe": 113.66,
      "home_bde": 101.4,
      "away_bde": 101.05,
      "home_bap": 66.7,
      "away_bap": 70.4,
      "home_conf": "B10",
      "away_conf": "B10",
      "kp_spread": -4.0,
      "kp_total": 150.0,
      "kp_home_score": 77.0,
      "kp_away_score": 73.0,
      "kp_home_wp": 66.0,
      "kp_pred_tempo": 69.0,
      "home_efg": 51.2244,
      "away_efg": 50.7985,
      "home_defg": 49.8838,
      "away_defg": 49.1051,
      "vegas_spread": -5.5,
      "consensus_spread": -5.2,
      "vegas_total": 150.83333333333334,
      "spread_book": "DraftKings",
      "books_count": 3,
      "edge": 1.2,
      "confidence": "NO_EDGE",
      "recommendation": "No edge",
      "bet_team": "USC",
      "bet_spread": 5.5
    },
    {
      "home_team": "Butler",
      "away_team": "Creighton",
      "home_abbrev": "BUT",
      "away_abbrev": "CREI",
      "date": "2026-03-04",
      "commence": "2026-03-04T23:00:00Z",
      "neutral_site": false,
      "model_spread": -3.6,
      "game_possessions": 67.7,
      "home_tt": 77.7,
      "away_tt": 74.1,
      "game_total": 151.8,
      "hca": 2.5,
      "home_bem": 11.24,
      "away_bem": 9.58,
      "home_boe": 117.83,
      "away_boe": 116.3,
      "home_bde": 106.59,
      "away_bde": 106.73,
      "home_bap": 68.4,
      "away_bap": 67.1,
      "home_conf": "BE",
      "away_conf": "BE",
      "kp_spread": -2.0,
      "kp_total": 156.0,
      "kp_home_score": 79.0,
      "kp_away_score": 77.0,
      "kp_home_wp": 60.0,
      "kp_pred_tempo": 68.0,
      "home_efg": 51.3226,
      "away_efg": 53.6827,
      "home_defg": 51.9576,
      "away_defg": 51.5336,
      "vegas_spread": -2.5,
      "consensus_spread": -2.5,
      "vegas_total": 155.5,
      "spread_book": "DraftKings",
      "books_count": 3,
      "edge": 1.1,
      "confidence": "NO_EDGE",
      "recommendation": "No edge",
      "bet_team": "Butler",
      "bet_spread": -2.5,
      "_locked": true
    },
    {
      "home_team": "Houston",
      "away_team": "Baylor",
      "home_abbrev": "HOU",
      "away_abbrev": "BAY",
      "date": "2026-03-04",
      "commence": "2026-03-05T02:00:00Z",
      "neutral_site": false,
      "model_spread": -14.6,
      "game_possessions": 65.5,
      "home_tt": 81.4,
      "away_tt": 66.8,
      "game_total": 148.2,
      "hca": 2.7,
      "home_bem": 33.55,
      "away_bem": 15.4,
      "home_boe": 126.07,
      "away_boe": 122.06,
      "home_bde": 92.51,
      "away_bde": 106.66,
      "home_bap": 63.2,
      "away_bap": 67.7,
      "home_conf": "B12",
      "away_conf": "B12",
      "kp_spread": -14.0,
      "kp_total": 146.0,
      "kp_home_score": 80.0,
      "kp_away_score": 66.0,
      "kp_home_wp": 90.0,
      "kp_pred_tempo": 64.0,
      "home_efg": 52.0011,
      "away_efg": 53.67,
      "home_defg": 46.729,
      "away_defg": 51.7141,
      "vegas_spread": -13.5,
      "consensus_spread": -13.5,
      "vegas_total": 143.5,
      "spread_book": "DraftKings",
      "books_count": 3,
      "edge": 1.1,
      "confidence": "NO_EDGE",
      "recommendation": "No edge",
      "bet_team": "Houston",
      "bet_spread": -13.5
    },
    {
      "home_team": "Davidson",
      "away_team": "Saint Joseph's",
      "home_abbrev": "DAV",
      "away_abbrev": "JOES",
      "date": "2026-03-04",
      "commence": "2026-03-05T00:00:00Z",
      "neutral_site": false,
      "model_spread": -3.5,
      "game_possessions": 65.7,
      "home_tt": 71.4,
      "away_tt": 67.9,
      "game_total": 139.4,
      "hca": 2.5,
      "home_bem": 6.96,
      "away_bem": 5.46,
      "home_boe": 111.4,
      "away_boe": 106.58,
      "home_bde": 104.44,
      "away_bde": 101.12,
      "home_bap": 63.6,
      "away_bap": 67.9,
      "home_conf": "A10",
      "away_conf": "A10",
      "kp_spread": -5.0,
      "kp_total": 133.0,
      "kp_home_score": 69.0,
      "kp_away_score": 64.0,
      "kp_home_wp": 65.0,
      "kp_pred_tempo": 65.0,
      "home_efg": 53.3155,
      "away_efg": 48.8293,
      "home_defg": 50.8225,
      "away_defg": 47.4076,
      "vegas_spread": -2.5,
      "consensus_spread": -2.5,
      "vegas_total": 135.83333333333334,
      "spread_book": "DraftKings",
      "books_count": 2,
      "edge": 1.0,
      "confidence": "NO_EDGE",
      "recommendation": "No edge",
      "bet_team": "Davidson",
      "bet_spread": -2.5
    },
    {
      "home_team": "SMU",
      "away_team": "Miami FL",
      "home_abbrev": "SMU",
      "away_abbrev": "MIA",
      "date": "2026-03-04",
      "commence": "2026-03-05T00:00:09Z",
      "neutral_site": false,
      "model_spread": -2.4,
      "game_possessions": 68.5,
      "home_tt": 78.6,
      "away_tt": 76.2,
      "game_total": 154.8,
      "hca": 2.6,
      "home_bem": 19.09,
      "away_bem": 19.48,
      "home_boe": 125.18,
      "away_boe": 120.17,
      "home_bde": 106.09,
      "away_bde": 100.69,
      "home_bap": 68.8,
      "away_bap": 68.1,
      "home_conf": "ACC",
      "away_conf": "ACC",
      "kp_spread": -2.0,
      "kp_total": 162.0,
      "kp_home_score": 82.0,
      "kp_away_score": 80.0,
      "kp_home_wp": 57.0,
      "kp_pred_tempo": 69.0,
      "home_efg": 56.3982,
      "away_efg": 55.9211,
      "home_defg": 50.9701,
      "away_defg": 50.8403,
      "vegas_spread": -1.5,
      "consensus_spread": -1.5,
      "vegas_total": 156.83333333333334,
      "spread_book": "FanDuel",
      "books_count": 3,
      "edge": 0.9,
      "confidence": "NO_EDGE",
      "recommendation": "No edge",
      "bet_team": "SMU",
      "bet_spread": -1.5
    },
    {
      "home_team": "Indiana",
      "away_team": "Minnesota",
      "home_abbrev": "IU",
      "away_abbrev": "MINN",
      "date": "2026-03-04",
      "commence": "2026-03-04T23:35:00Z",
      "neutral_site": false,
      "model_spread": -5.8,
      "game_possessions": 64.2,
      "home_tt": 74.5,
      "away_tt": 68.6,
      "game_total": 143.1,
      "hca": 2.7,
      "home_bem": 19.16,
      "away_bem": 14.32,
      "home_boe": 122.25,
      "away_boe": 116.53,
      "home_bde": 103.09,
      "away_bde": 102.21,
      "home_bap": 66.0,
      "away_bap": 62.5,
      "home_conf": "B10",
      "away_conf": "B10",
      "kp_spread": -6.0,
      "kp_total": 140.0,
      "kp_home_score": 73.0,
      "kp_away_score": 67.0,
      "kp_home_wp": 71.0,
      "kp_pred_tempo": 62.0,
      "home_efg": 55.7821,
      "away_efg": 54.406,
      "home_defg": 48.5979,
      "away_defg": 51.3019,
      "vegas_spread": -6.5,
      "consensus_spread": -6.5,
      "vegas_total": 138.5,
      "spread_book": "DraftKings",
      "books_count": 3,
      "edge": 0.7,
      "confidence": "NO_EDGE",
      "recommendation": "No edge",
      "bet_team": "Minnesota",
      "bet_spread": 6.5
    },
    {
      "home_team": "Arkansas",
      "away_team": "Texas",
      "home_abbrev": "ARK",
      "away_abbrev": "TEX",
      "date": "2026-03-04",
      "commence": "2026-03-05T00:00:07Z",
      "neutral_site": false,
      "model_spread": -6.1,
      "game_possessions": 68.6,
      "home_tt": 82.8,
      "away_tt": 76.7,
      "game_total": 159.5,
      "hca": 2.7,
      "home_bem": 25.53,
      "away_bem": 20.56,
      "home_boe": 127.94,
      "away_boe": 126.85,
      "home_bde": 102.41,
      "away_bde": 106.29,
      "home_bap": 70.8,
      "away_bap": 66.3,
      "home_conf": "SEC",
      "away_conf": "SEC",
      "kp_spread": -6.0,
      "kp_total": 170.0,
      "kp_home_score": 88.0,
      "kp_away_score": 82.0,
      "kp_home_wp": 73.0,
      "kp_pred_tempo": 69.0,
      "home_efg": 56.3573,
      "away_efg": 54.8849,
      "home_defg": 51.4107,
      "away_defg": 50.7444,
      "vegas_spread": -6.5,
      "consensus_spread": -6.5,
      "vegas_total": 164.5,
      "spread_book": "FanDuel",
      "books_count": 3,
      "edge": 0.4,
      "confidence": "NO_EDGE",
      "recommendation": "No edge",
      "bet_team": "Texas",
      "bet_spread": 6.5
    },
    {
      "home_team": "Wisconsin",
      "away_team": "Maryland",
      "home_abbrev": "WIS",
      "away_abbrev": "MD",
      "date": "2026-03-04",
      "commence": "2026-03-05T01:00:00Z",
      "neutral_site": false,
      "model_spread": -14.9,
      "game_possessions": 67.9,
      "home_tt": 84.2,
      "away_tt": 69.3,
      "game_total": 153.5,
      "hca": 2.5,
      "home_bem": 22.2,
      "away_bem": 3.96,
      "home_boe": 124.72,
      "away_boe": 111.2,
      "home_bde": 102.51,
      "away_bde": 107.24,
      "home_bap": 69.3,
      "away_bap": 66.5,
      "home_conf": "B10",
      "away_conf": "B10",
      "kp_spread": -15.0,
      "kp_total": 155.0,
      "kp_home_score": 85.0,
      "kp_away_score": 70.0,
      "kp_home_wp": 91.0,
      "kp_pred_tempo": 68.0,
      "home_efg": 53.9956,
      "away_efg": 48.1895,
      "home_defg": 51.373,
      "away_defg": 54.5838,
      "vegas_spread": -14.5,
      "consensus_spread": -14.2,
      "vegas_total": 153.83333333333334,
      "spread_book": "DraftKings",
      "books_count": 3,
      "edge": 0.4,
      "confidence": "NO_EDGE",
      "recommendation": "No edge",
      "bet_team": "Wisconsin",
      "bet_spread": -14.5
    },
    {
      "home_team": "Central Connecticut",
      "away_team": "Wagner",
      "home_abbrev": "CCSU",
      "away_abbrev": "WAG",
      "date": "2026-03-04",
      "commence": "2026-03-05T00:00:00Z",
      "neutral_site": false,
      "model_spread": -3.3,
      "game_possessions": 65.2,
      "home_tt": 73.8,
      "away_tt": 70.5,
      "game_total": 144.3,
      "hca": 2.5,
      "home_bem": -12.42,
      "away_bem": -13.77,
      "home_boe": 105.25,
      "away_boe": 102.93,
      "home_bde": 117.67,
      "away_bde": 116.7,
      "home_bap": 64.9,
      "away_bap": 65.5,
      "home_conf": "NEC",
      "away_conf": "NEC",
      "kp_spread": -3.0,
      "kp_total": 143.0,
      "kp_home_score": 73.0,
      "kp_away_score": 70.0,
      "kp_home_wp": 60.0,
      "kp_pred_tempo": 64.0,
      "home_efg": 51.9732,
      "away_efg": 50.0677,
      "home_defg": 50.1869,
      "away_defg": 50.9629,
      "vegas_spread": -3.5,
      "consensus_spread": -3.5,
      "vegas_total": 139.5,
      "spread_book": "BetMGM",
      "books_count": 2,
      "edge": 0.2,
      "confidence": "NO_EDGE",
      "recommendation": "No edge",
      "bet_team": "Wagner",
      "bet_spread": 3.5
    },
    {
      "home_team": "West Georgia",
      "away_team": "North Florida",
      "home_abbrev": "WGA",
      "away_abbrev": "UNF",
      "date": "2026-03-04",
      "commence": "2026-03-05T00:30:00Z",
      "neutral_site": true,
      "model_spread": -3.3,
      "game_possessions": 69.5,
      "home_tt": 79.9,
      "away_tt": 76.5,
      "game_total": 156.4,
      "hca": 0,
      "home_bem": -12.06,
      "away_bem": -16.83,
      "home_boe": 102.77,
      "away_boe": 107.01,
      "home_bde": 114.83,
      "away_bde": 123.84,
      "home_bap": 68.8,
      "away_bap": 70.1,
      "home_conf": "ASun",
      "away_conf": "ASun",
      "kp_spread": -3.0,
      "kp_total": 163.0,
      "kp_home_score": 83.0,
      "kp_away_score": 80.0,
      "kp_home_wp": 62.0,
      "kp_pred_tempo": 71.0,
      "home_efg": 49.7148,
      "away_efg": 53.1376,
      "home_defg": 53.75,
      "away_defg": 56.1562,
      "vegas_spread": -3.5,
      "consensus_spread": -3.5,
      "vegas_total": 160.5,
      "spread_book": "DraftKings",
      "books_count": 3,
      "edge": 0.2,
      "confidence": "NO_EDGE",
      "recommendation": "No edge",
      "bet_team": "North Florida",
      "bet_spread": 3.5
    },
    {
      "home_team": "North Texas",
      "away_team": "Rice",
      "home_abbrev": "UNT",
      "away_abbrev": "RICE",
      "date": "2026-03-04",
      "commence": "2026-03-05T01:00:00Z",
      "neutral_site": false,
      "model_spread": -6.7,
      "game_possessions": 65.1,
      "home_tt": 73.5,
      "away_tt": 66.8,
      "game_total": 140.3,
      "hca": 2.5,
      "home_bem": 1.77,
      "away_bem": -4.67,
      "home_boe": 104.0,
      "away_boe": 109.18,
      "home_bde": 102.23,
      "away_bde": 113.85,
      "home_bap": 64.7,
      "away_bap": 65.5,
      "home_conf": "Amer",
      "away_conf": "Amer",
      "kp_spread": -8.0,
      "kp_total": 134.0,
      "kp_home_score": 71.0,
      "kp_away_score": 63.0,
      "kp_home_wp": 77.0,
      "kp_pred_tempo": 64.0,
      "home_efg": 46.4107,
      "away_efg": 48.7828,
      "home_defg": 48.8079,
      "away_defg": 51.6284,
      "vegas_spread": -6.5,
      "consensus_spread": -6.5,
      "vegas_total": 137.5,
      "spread_book": "DraftKings",
      "books_count": 3,
      "edge": 0.2,
      "confidence": "NO_EDGE",
      "recommendation": "No edge",
      "bet_team": "North Texas",
      "bet_spread": -6.5
    },
    {
      "home_team": "Bellarmine",
      "away_team": "Jacksonville",
      "home_abbrev": "BELL",
      "away_abbrev": "JAX",
      "date": "2026-03-04",
      "commence": "2026-03-04T17:00:00Z",
      "neutral_site": true,
      "model_spread": 0.6,
      "game_possessions": 63.8,
      "home_tt": 72.9,
      "away_tt": 73.5,
      "game_total": 146.5,
      "hca": 0,
      "home_bem": -11.53,
      "away_bem": -10.6,
      "home_boe": 115.28,
      "away_boe": 103.07,
      "home_bde": 126.81,
      "away_bde": 113.67,
      "home_bap": 64.5,
      "away_bap": 63.1,
      "home_conf": "ASun",
      "away_conf": "ASun",
      "kp_spread": -2.0,
      "kp_total": 148.0,
      "kp_home_score": 75.0,
      "kp_away_score": 73.0,
      "kp_home_wp": 55.0,
      "kp_pred_tempo": 62.0,
      "home_efg": 59.3647,
      "away_efg": 49.9691,
      "home_defg": 59.3267,
      "away_defg": 54.6036,
      "vegas_spread": -1.5,
      "consensus_spread": -1.5,
      "vegas_total": 146.16666666666666,
      "spread_book": "FanDuel",
      "books_count": 3,
      "edge": 2.1,
      "confidence": "NO_EDGE",
      "recommendation": "No edge",
      "bet_team": "Jacksonville",
      "bet_spread": 1.5,
      "_locked": true
    },
    {
      "home_team": "Florida Gulf Coast",
      "away_team": "North Alabama",
      "home_abbrev": "FGCU",
      "away_abbrev": "UNA",
      "date": "2026-03-04",
      "commence": "2026-03-04T19:30:00Z",
      "neutral_site": true,
      "model_spread": -7.1,
      "game_possessions": 66.2,
      "home_tt": 76.7,
      "away_tt": 69.7,
      "game_total": 146.4,
      "hca": 0,
      "home_bem": -7.96,
      "away_bem": -18.61,
      "home_boe": 105.79,
      "away_boe": 100.11,
      "home_bde": 113.76,
      "away_bde": 118.72,
      "home_bap": 67.7,
      "away_bap": 64.8,
      "home_conf": "ASun",
      "away_conf": "ASun",
      "kp_spread": -7.0,
      "kp_total": 145.0,
      "kp_home_score": 76.0,
      "kp_away_score": 69.0,
      "kp_home_wp": 74.0,
      "kp_pred_tempo": 66.0,
      "home_efg": 52.1959,
      "away_efg": 47.9761,
      "home_defg": 53.8622,
      "away_defg": 55.3617,
      "vegas_spread": -7.5,
      "consensus_spread": -7.5,
      "vegas_total": 141.5,
      "spread_book": "FanDuel",
      "books_count": 3,
      "edge": 0.4,
      "confidence": "NO_EDGE",
      "recommendation": "No edge",
      "bet_team": "North Alabama",
      "bet_spread": 7.5,
      "_locked": true
    },
    {
      "home_team": "LIU",
      "away_team": "Chicago St.",
      "home_abbrev": "LIU",
      "away_abbrev": "CHST",
      "date": "2026-03-04",
      "commence": "2026-03-05T00:00Z",
      "neutral_site": false,
      "model_spread": -12.1,
      "game_possessions": 66.8,
      "home_tt": 78.6,
      "away_tt": 66.5,
      "game_total": 145.1,
      "hca": 2.4,
      "home_bem": -4.94,
      "away_bem": -19.47,
      "home_boe": 104.1,
      "away_boe": 98.62,
      "home_bde": 109.04,
      "away_bde": 118.09,
      "home_bap": 68.0,
      "away_bap": 65.5,
      "home_conf": "NEC",
      "away_conf": "NEC",
      "kp_spread": -13.0,
      "kp_total": 141.0,
      "kp_home_score": 77.0,
      "kp_away_score": 64.0,
      "kp_home_wp": 89.0,
      "kp_pred_tempo": 66.0,
      "home_efg": 53.1897,
      "away_efg": 45.0664,
      "home_defg": 50.0278,
      "away_defg": 56.5619,
      "vegas_spread": null,
      "consensus_spread": null,
      "vegas_total": null,
      "spread_book": "",
      "books_count": 0,
      "edge": 0,
      "confidence": "NO_ODDS",
      "recommendation": "NO ODDS",
      "bet_team": "",
      "bet_spread": 0
    },
    {
      "home_team": "Robert Morris",
      "away_team": "Youngstown St.",
      "home_abbrev": "RMU",
      "away_abbrev": "YSU",
      "date": "2026-03-04",
      "commence": "2026-03-05T00:00Z",
      "neutral_site": false,
      "model_spread": -4.7,
      "game_possessions": 65.9,
      "home_tt": 74.5,
      "away_tt": 69.8,
      "game_total": 144.3,
      "hca": 2.5,
      "home_bem": 0.82,
      "away_bem": -2.52,
      "home_boe": 110.86,
      "away_boe": 106.88,
      "home_bde": 110.03,
      "away_bde": 109.4,
      "home_bap": 64.6,
      "away_bap": 67.1,
      "home_conf": "Horz",
      "away_conf": "Horz",
      "kp_spread": -6.0,
      "kp_total": 142.0,
      "kp_home_score": 74.0,
      "kp_away_score": 68.0,
      "kp_home_wp": 71.0,
      "kp_pred_tempo": 65.0,
      "home_efg": 54.9539,
      "away_efg": 54.2105,
      "home_defg": 50.5835,
      "away_defg": 52.0938,
      "vegas_spread": null,
      "consensus_spread": null,
      "vegas_total": null,
      "spread_book": "",
      "books_count": 0,
      "edge": 0,
      "confidence": "NO_ODDS",
      "recommendation": "NO ODDS",
      "bet_team": "",
      "bet_spread": 0
    },
    {
      "home_team": "Wright St.",
      "away_team": "Cleveland St.",
      "home_abbrev": "WRST",
      "away_abbrev": "CLE",
      "date": "2026-03-04",
      "commence": "2026-03-05T00:00Z",
      "neutral_site": false,
      "model_spread": -13.5,
      "game_possessions": 68.0,
      "home_tt": 85.5,
      "away_tt": 72.0,
      "game_total": 157.6,
      "hca": 2.6,
      "home_bem": 2.43,
      "away_bem": -13.56,
      "home_boe": 112.85,
      "away_boe": 110.29,
      "home_bde": 110.42,
      "away_bde": 123.85,
      "home_bap": 66.6,
      "away_bap": 69.4,
      "home_conf": "Horz",
      "away_conf": "Horz",
      "kp_spread": -13.0,
      "kp_total": 165.0,
      "kp_home_score": 89.0,
      "kp_away_score": 76.0,
      "kp_home_wp": 89.0,
      "kp_pred_tempo": 69.0,
      "home_efg": 54.3517,
      "away_efg": 54.6386,
      "home_defg": 52.9603,
      "away_defg": 57.1389,
      "vegas_spread": null,
      "consensus_spread": null,
      "vegas_total": null,
      "spread_book": "",
      "books_count": 0,
      "edge": 0,
      "confidence": "NO_ODDS",
      "recommendation": "NO ODDS",
      "bet_team": "",
      "bet_spread": 0
    },
    {
      "home_team": "George Washington",
      "away_team": "St. Bonaventure",
      "home_abbrev": "GW",
      "away_abbrev": "SBU",
      "date": "2026-03-04",
      "commence": "2026-03-05T00:00Z",
      "neutral_site": false,
      "model_spread": -10.2,
      "game_possessions": 68.0,
      "home_tt": 83.3,
      "away_tt": 73.1,
      "game_total": 156.4,
      "hca": 2.5,
      "home_bem": 11.09,
      "away_bem": -0.1,
      "home_boe": 119.23,
      "away_boe": 114.13,
      "home_bde": 108.15,
      "away_bde": 114.23,
      "home_bap": 69.2,
      "away_bap": 66.9,
      "home_conf": "A10",
      "away_conf": "A10",
      "kp_spread": -9.0,
      "kp_total": 163.0,
      "kp_home_score": 86.0,
      "kp_away_score": 77.0,
      "kp_home_wp": 81.0,
      "kp_pred_tempo": 68.0,
      "home_efg": 55.5853,
      "away_efg": 52.7515,
      "home_defg": 52.3559,
      "away_defg": 54.3082,
      "vegas_spread": null,
      "consensus_spread": null,
      "vegas_total": null,
      "spread_book": "",
      "books_count": 0,
      "edge": 0,
      "confidence": "NO_ODDS",
      "recommendation": "NO ODDS",
      "bet_team": "",
      "bet_spread": 0
    },
    {
      "home_team": "Saint Louis",
      "away_team": "Loyola Chicago",
      "home_abbrev": "SLU",
      "away_abbrev": "LUC",
      "date": "2026-03-04",
      "commence": "2026-03-05T01:00Z",
      "neutral_site": false,
      "model_spread": -25.2,
      "game_possessions": 68.8,
      "home_tt": 90.1,
      "away_tt": 64.9,
      "game_total": 155.0,
      "hca": 2.7,
      "home_bem": 20.9,
      "away_bem": -11.81,
      "home_boe": 121.02,
      "away_boe": 102.67,
      "home_bde": 100.13,
      "away_bde": 114.48,
      "home_bap": 71.3,
      "away_bap": 66.3,
      "home_conf": "A10",
      "away_conf": "A10",
      "kp_spread": -28.0,
      "kp_total": 154.0,
      "kp_home_score": 91.0,
      "kp_away_score": 63.0,
      "kp_home_wp": 99.0,
      "kp_pred_tempo": 70.0,
      "home_efg": 60.4327,
      "away_efg": 49.1504,
      "home_defg": 43.5958,
      "away_defg": 52.4189,
      "vegas_spread": null,
      "consensus_spread": null,
      "vegas_total": null,
      "spread_book": "",
      "books_count": 0,
      "edge": 0,
      "confidence": "NO_ODDS",
      "recommendation": "NO ODDS",
      "bet_team": "",
      "bet_spread": 0
    },
    {
      "home_team": "Oral Roberts",
      "away_team": "Kansas City",
      "home_abbrev": "ORU",
      "away_abbrev": "KC",
      "date": "2026-03-04",
      "commence": "2026-03-05T01:00Z",
      "neutral_site": true,
      "model_spread": -7.1,
      "game_possessions": 68.5,
      "home_tt": 77.3,
      "away_tt": 70.2,
      "game_total": 147.5,
      "hca": 0,
      "home_bem": -13.23,
      "away_bem": -23.54,
      "home_boe": 101.66,
      "away_boe": 93.31,
      "home_bde": 114.89,
      "away_bde": 116.85,
      "home_bap": 67.5,
      "away_bap": 69.6,
      "home_conf": "Sum",
      "away_conf": "Sum",
      "kp_spread": -8.0,
      "kp_total": 144.0,
      "kp_home_score": 76.0,
      "kp_away_score": 68.0,
      "kp_home_wp": 75.0,
      "kp_pred_tempo": 70.0,
      "home_efg": 49.193,
      "away_efg": 46.0147,
      "home_defg": 54.507,
      "away_defg": 56.1069,
      "vegas_spread": null,
      "consensus_spread": null,
      "vegas_total": null,
      "spread_book": "",
      "books_count": 0,
      "edge": 0,
      "confidence": "NO_ODDS",
      "recommendation": "NO ODDS",
      "bet_team": "",
      "bet_spread": 0
    },
    {
      "home_team": "Pittsburgh",
      "away_team": "Florida St.",
      "home_abbrev": "PITT",
      "away_abbrev": "FSU",
      "date": "2026-03-04",
      "commence": "2026-03-05T02:00Z",
      "neutral_site": false,
      "model_spread": 1.1,
      "game_possessions": 67.1,
      "home_tt": 73.3,
      "away_tt": 74.5,
      "game_total": 147.8,
      "hca": 2.5,
      "home_bem": 6.8,
      "away_bem": 12.2,
      "home_boe": 112.17,
      "away_boe": 116.5,
      "home_bde": 105.38,
      "away_bde": 104.31,
      "home_bap": 63.8,
      "away_bap": 70.5,
      "home_conf": "ACC",
      "away_conf": "ACC",
      "kp_spread": 1.0,
      "kp_total": 149.0,
      "kp_home_score": 74.0,
      "kp_away_score": 75.0,
      "kp_home_wp": 49.0,
      "kp_pred_tempo": 67.0,
      "home_efg": 50.9025,
      "away_efg": 50.9071,
      "home_defg": 52.7882,
      "away_defg": 52.1579,
      "vegas_spread": null,
      "consensus_spread": null,
      "vegas_total": null,
      "spread_book": "",
      "books_count": 0,
      "edge": 0,
      "confidence": "NO_ODDS",
      "recommendation": "NO ODDS",
      "bet_team": "",
      "bet_spread": 0
    },
    {
      "home_team": "Lindenwood",
      "away_team": "Little Rock",
      "home_abbrev": "LIN",
      "away_abbrev": "LR",
      "date": "2026-03-04",
      "commence": "2026-03-05T02:30Z",
      "neutral_site": true,
      "model_spread": -3.8,
      "game_possessions": 69.2,
      "home_tt": 76.8,
      "away_tt": 73.0,
      "game_total": 149.8,
      "hca": 0,
      "home_bem": -8.79,
      "away_bem": -14.27,
      "home_boe": 101.2,
      "away_boe": 102.85,
      "home_bde": 109.99,
      "away_bde": 117.12,
      "home_bap": 72.2,
      "away_bap": 66.1,
      "home_conf": "OVC",
      "away_conf": "OVC",
      "kp_spread": -3.0,
      "kp_total": 151.0,
      "kp_home_score": 77.0,
      "kp_away_score": 74.0,
      "kp_home_wp": 60.0,
      "kp_pred_tempo": 71.0,
      "home_efg": 48.8277,
      "away_efg": 49.9408,
      "home_defg": 49.6454,
      "away_defg": 52.4175,
      "vegas_spread": null,
      "consensus_spread": null,
      "vegas_total": null,
      "spread_book": "",
      "books_count": 0,
      "edge": 0,
      "confidence": "NO_ODDS",
      "recommendation": "NO ODDS",
      "bet_team": "",
      "bet_spread": 0
    },
    {
      "home_team": "New Mexico",
      "away_team": "Colorado St.",
      "home_abbrev": "UNM",
      "away_abbrev": "CSU",
      "date": "2026-03-04",
      "commence": "2026-03-05T03:00Z",
      "neutral_site": false,
      "model_spread": -7.3,
      "game_possessions": 66.1,
      "home_tt": 77.8,
      "away_tt": 70.5,
      "game_total": 148.3,
      "hca": 2.7,
      "home_bem": 16.07,
      "away_bem": 9.16,
      "home_boe": 116.54,
      "away_boe": 119.51,
      "home_bde": 100.47,
      "away_bde": 110.35,
      "home_bap": 69.6,
      "away_bap": 62.5,
      "home_conf": "MWC",
      "away_conf": "MWC",
      "kp_spread": -9.0,
      "kp_total": 149.0,
      "kp_home_score": 79.0,
      "kp_away_score": 70.0,
      "kp_home_wp": 79.0,
      "kp_pred_tempo": 65.0,
      "home_efg": 53.6826,
      "away_efg": 58.6532,
      "home_defg": 48.7408,
      "away_defg": 53.2237,
      "vegas_spread": null,
      "consensus_spread": null,
      "vegas_total": null,
      "spread_book": "",
      "books_count": 0,
      "edge": 0,
      "confidence": "NO_ODDS",
      "recommendation": "NO ODDS",
      "bet_team": "",
      "bet_spread": 0
    }
  ]
}