{
  "generated_at": "2026-03-21 11:00",
  "sport": "NCAAB",
  "model_version": "v1.1.1",
  "ratings_source": "KenPom + Bart Torvik (35/65 blend)",
  "torvik_active": true,
  "odds_api_remaining": 346,
  "parameters": {
    "kp_weight": 0.35,
    "bt_weight": 0.65,
    "default_hca": 2.5,
    "high_edge_threshold": 5.0,
    "medium_edge_threshold": 2.5
  },
  "summary": {
    "total_games": 10,
    "high_confidence": 0,
    "medium_confidence": 0,
    "no_edge": 9,
    "no_odds": 1
  },
  "predictions": [
    {
      "home_team": "Gonzaga",
      "away_team": "Texas",
      "home_abbrev": "GONZ",
      "away_abbrev": "TEX",
      "date": "2026-03-21",
      "commence": "2026-03-21T23:10:00Z",
      "neutral_site": true,
      "model_spread": -4.9,
      "game_possessions": 67.9,
      "home_tt": 78.0,
      "away_tt": 73.1,
      "game_total": 151.1,
      "hca": 0,
      "home_bem": 26.06,
      "away_bem": 18.84,
      "home_boe": 120.17,
      "away_boe": 123.66,
      "home_bde": 94.1,
      "away_bde": 104.82,
      "home_bap": 68.8,
      "away_bap": 67.0,
      "home_conf": "WCC",
      "away_conf": "SEC",
      "kp_spread": -5.0,
      "kp_total": 153.0,
      "kp_home_score": 79.0,
      "kp_away_score": 74.0,
      "kp_home_wp": 68.0,
      "kp_pred_tempo": 68.0,
      "home_efg": 55.8469,
      "away_efg": 53.7918,
      "home_defg": 45.9714,
      "away_defg": 50.8107,
      "vegas_spread": -6.5,
      "consensus_spread": -6.5,
      "vegas_total": 147.5,
      "spread_book": "DraftKings",
      "books_count": 3,
      "edge": 1.6,
      "confidence": "NO_EDGE",
      "recommendation": "No edge",
      "bet_team": "Texas",
      "bet_spread": 6.5
    },
    {
      "home_team": "Houston",
      "away_team": "Texas A&M",
      "home_abbrev": "HOU",
      "away_abbrev": "TA&M",
      "date": "2026-03-21",
      "commence": "2026-03-21T22:10:00Z",
      "neutral_site": true,
      "model_spread": -9.4,
      "game_possessions": 67.0,
      "home_tt": 78.6,
      "away_tt": 69.3,
      "game_total": 147.9,
      "hca": 0,
      "home_bem": 33.51,
      "away_bem": 19.54,
      "home_boe": 125.03,
      "away_boe": 119.86,
      "home_bde": 91.52,
      "away_bde": 100.32,
      "home_bap": 63.4,
      "away_bap": 70.6,
      "home_conf": "B12",
      "away_conf": "SEC",
      "kp_spread": -10.0,
      "kp_total": 144.0,
      "kp_home_score": 77.0,
      "kp_away_score": 67.0,
      "kp_home_wp": 80.0,
      "kp_pred_tempo": 66.0,
      "home_efg": 52.2454,
      "away_efg": 54.1332,
      "home_defg": 46.2022,
      "away_defg": 50.7129,
      "vegas_spread": -10.5,
      "consensus_spread": -10.5,
      "vegas_total": 142.5,
      "spread_book": "DraftKings",
      "books_count": 3,
      "edge": 1.1,
      "confidence": "NO_EDGE",
      "recommendation": "No edge",
      "bet_team": "Texas A&M",
      "bet_spread": 10.5
    },
    {
      "home_team": "Nevada",
      "away_team": "Liberty",
      "home_abbrev": "NEV",
      "away_abbrev": "LIB",
      "date": "2026-03-21",
      "commence": "2026-03-22T01:00:00Z",
      "neutral_site": false,
      "model_spread": -6.4,
      "game_possessions": 65.1,
      "home_tt": 76.7,
      "away_tt": 70.4,
      "game_total": 147.1,
      "hca": 2.5,
      "home_bem": 11.07,
      "away_bem": 5.1,
      "home_boe": 114.99,
      "away_boe": 118.1,
      "home_bde": 103.92,
      "away_bde": 113.0,
      "home_bap": 66.1,
      "away_bap": 64.1,
      "home_conf": "MWC",
      "away_conf": "CUSA",
      "kp_spread": -8.0,
      "kp_total": 148.0,
      "kp_home_score": 78.0,
      "kp_away_score": 70.0,
      "kp_home_wp": 78.0,
      "kp_pred_tempo": 64.0,
      "home_efg": 49.9247,
      "away_efg": 59.6344,
      "home_defg": 51.2233,
      "away_defg": 52.7393,
      "vegas_spread": -7.5,
      "consensus_spread": -7.5,
      "vegas_total": 147.5,
      "spread_book": "DraftKings",
      "books_count": 3,
      "edge": 1.1,
      "confidence": "NO_EDGE",
      "recommendation": "No edge",
      "bet_team": "Liberty",
      "bet_spread": 7.5
    },
    {
      "home_team": "Arkansas",
      "away_team": "High Point",
      "home_abbrev": "ARK",
      "away_abbrev": "HPU",
      "date": "2026-03-21",
      "commence": "2026-03-22T01:45:00Z",
      "neutral_site": true,
      "model_spread": -12.3,
      "game_possessions": 70.6,
      "home_tt": 87.5,
      "away_tt": 75.2,
      "game_total": 162.7,
      "hca": 0,
      "home_bem": 26.53,
      "away_bem": 9.06,
      "home_boe": 128.24,
      "away_boe": 116.49,
      "home_bde": 101.71,
      "away_bde": 107.43,
      "home_bap": 71.1,
      "away_bap": 70.0,
      "home_conf": "SEC",
      "away_conf": "BSth",
      "kp_spread": -12.0,
      "kp_total": 172.0,
      "kp_home_score": 92.0,
      "kp_away_score": 80.0,
      "kp_home_wp": 87.0,
      "kp_pred_tempo": 73.0,
      "home_efg": 56.4996,
      "away_efg": 54.6169,
      "home_defg": 51.3821,
      "away_defg": 50.218,
      "vegas_spread": -11.5,
      "consensus_spread": -11.5,
      "vegas_total": 169.5,
      "spread_book": "DraftKings",
      "books_count": 3,
      "edge": 0.8,
      "confidence": "NO_EDGE",
      "recommendation": "No edge",
      "bet_team": "Arkansas",
      "bet_spread": -11.5
    },
    {
      "home_team": "Duke",
      "away_team": "TCU",
      "home_abbrev": "DUKE",
      "away_abbrev": "TCU",
      "date": "2026-03-21",
      "commence": "2026-03-21T21:15:00Z",
      "neutral_site": true,
      "model_spread": -13.2,
      "game_possessions": 66.6,
      "home_tt": 79.6,
      "away_tt": 66.4,
      "game_total": 146.0,
      "hca": 0,
      "home_bem": 36.39,
      "away_bem": 16.5,
      "home_boe": 127.34,
      "away_boe": 115.08,
      "home_bde": 90.96,
      "away_bde": 98.58,
      "home_bap": 65.7,
      "away_bap": 67.5,
      "home_conf": "ACC",
      "away_conf": "B12",
      "kp_spread": -13.0,
      "kp_total": 139.0,
      "kp_home_score": 76.0,
      "kp_away_score": 63.0,
      "kp_home_wp": 88.0,
      "kp_pred_tempo": 66.0,
      "home_efg": 56.4303,
      "away_efg": 50.801,
      "home_defg": 46.1538,
      "away_defg": 50.9105,
      "vegas_spread": -12.5,
      "consensus_spread": -12.2,
      "vegas_total": 139.83333333333334,
      "spread_book": "DraftKings",
      "books_count": 3,
      "edge": 0.7,
      "confidence": "NO_EDGE",
      "recommendation": "No edge",
      "bet_team": "Duke",
      "bet_spread": -12.5
    },
    {
      "home_team": "Nebraska",
      "away_team": "Vanderbilt",
      "home_abbrev": "NEB",
      "away_abbrev": "VAN",
      "date": "2026-03-21",
      "commence": "2026-03-22T00:45:00Z",
      "neutral_site": true,
      "model_spread": 1.9,
      "game_possessions": 67.8,
      "home_tt": 73.4,
      "away_tt": 75.3,
      "game_total": 148.6,
      "hca": 0,
      "home_bem": 25.0,
      "away_bem": 27.85,
      "home_boe": 117.66,
      "away_boe": 127.46,
      "home_bde": 92.66,
      "away_bde": 99.61,
      "home_bap": 66.7,
      "away_bap": 68.9,
      "home_conf": "B10",
      "away_conf": "SEC",
      "kp_spread": 1.0,
      "kp_total": 149.0,
      "kp_home_score": 74.0,
      "kp_away_score": 75.0,
      "kp_home_wp": 48.0,
      "kp_pred_tempo": 68.0,
      "home_efg": 55.3874,
      "away_efg": 55.3839,
      "home_defg": 47.5406,
      "away_defg": 48.5687,
      "vegas_spread": 1.5,
      "consensus_spread": 1.5,
      "vegas_total": 146.5,
      "spread_book": "DraftKings",
      "books_count": 3,
      "edge": 0.4,
      "confidence": "NO_EDGE",
      "recommendation": "No edge",
      "bet_team": "Vanderbilt",
      "bet_spread": -1.5
    },
    {
      "home_team": "UNC Wilmington",
      "away_team": "Dayton",
      "home_abbrev": "UNCW",
      "away_abbrev": "DAY",
      "date": "2026-03-21",
      "commence": "2026-03-21T23:00:00Z",
      "neutral_site": false,
      "model_spread": 2.1,
      "game_possessions": 65.9,
      "home_tt": 69.9,
      "away_tt": 72.0,
      "game_total": 142.0,
      "hca": 2.4,
      "home_bem": 4.9,
      "away_bem": 11.7,
      "home_boe": 110.85,
      "away_boe": 111.67,
      "home_bde": 105.95,
      "away_bde": 99.96,
      "home_bap": 65.1,
      "away_bap": 66.8,
      "home_conf": "CAA",
      "away_conf": "A10",
      "kp_spread": 1.0,
      "kp_total": 137.0,
      "kp_home_score": 68.0,
      "kp_away_score": 69.0,
      "kp_home_wp": 45.0,
      "kp_pred_tempo": 65.0,
      "home_efg": 50.5833,
      "away_efg": 51.9519,
      "home_defg": 47.0885,
      "away_defg": 50.9891,
      "vegas_spread": 2.5,
      "consensus_spread": 2.5,
      "vegas_total": 139.5,
      "spread_book": "DraftKings",
      "books_count": 3,
      "edge": 0.4,
      "confidence": "NO_EDGE",
      "recommendation": "No edge",
      "bet_team": "UNC Wilmington",
      "bet_spread": 2.5
    },
    {
      "home_team": "Illinois",
      "away_team": "VCU",
      "home_abbrev": "ILL",
      "away_abbrev": "VCU",
      "date": "2026-03-21",
      "commence": "2026-03-21T23:50:00Z",
      "neutral_site": true,
      "model_spread": -10.8,
      "game_possessions": 67.2,
      "home_tt": 82.4,
      "away_tt": 71.7,
      "game_total": 154.1,
      "hca": 0,
      "home_bem": 33.33,
      "away_bem": 17.31,
      "home_boe": 132.4,
      "away_boe": 119.55,
      "home_bde": 99.07,
      "away_bde": 102.24,
      "home_bap": 65.7,
      "away_bap": 68.6,
      "home_conf": "B10",
      "away_conf": "A10",
      "kp_spread": -9.0,
      "kp_total": 157.0,
      "kp_home_score": 83.0,
      "kp_away_score": 74.0,
      "kp_home_wp": 81.0,
      "kp_pred_tempo": 67.0,
      "home_efg": 55.2478,
      "away_efg": 54.0686,
      "home_defg": 47.7523,
      "away_defg": 48.7946,
      "vegas_spread": -10.5,
      "consensus_spread": -10.5,
      "vegas_total": 149.83333333333334,
      "spread_book": "DraftKings",
      "books_count": 3,
      "edge": 0.3,
      "confidence": "NO_EDGE",
      "recommendation": "No edge",
      "bet_team": "Illinois",
      "bet_spread": -10.5
    },
    {
      "home_team": "Michigan",
      "away_team": "Saint Louis",
      "home_abbrev": "MICH",
      "away_abbrev": "SLU",
      "date": "2026-03-21",
      "commence": "2026-03-21T16:10:00Z",
      "neutral_site": true,
      "model_spread": -12.3,
      "game_possessions": 71.2,
      "home_tt": 85.8,
      "away_tt": 73.5,
      "game_total": 159.2,
      "hca": 0,
      "home_bem": 36.45,
      "away_bem": 19.18,
      "home_boe": 127.76,
      "away_boe": 120.14,
      "home_bde": 91.32,
      "away_bde": 100.95,
      "home_bap": 71.1,
      "away_bap": 71.2,
      "home_conf": "B10",
      "away_conf": "A10",
      "kp_spread": -13.0,
      "kp_total": 161.0,
      "kp_home_score": 87.0,
      "kp_away_score": 74.0,
      "kp_home_wp": 88.0,
      "kp_pred_tempo": 74.0,
      "home_efg": 58.5673,
      "away_efg": 59.924,
      "home_defg": 44.9955,
      "away_defg": 44.6491,
      "vegas_spread": -12.5,
      "consensus_spread": -12.5,
      "vegas_total": 161.5,
      "spread_book": "DraftKings",
      "books_count": 3,
      "edge": 0.2,
      "confidence": "NO_EDGE",
      "recommendation": "No edge",
      "bet_team": "Saint Louis",
      "bet_spread": 12.5
    },
    {
      "home_team": "Michigan St.",
      "away_team": "Louisville",
      "home_abbrev": "MSU",
      "away_abbrev": "LOU",
      "date": "2026-03-21",
      "commence": "2026-03-21T18:45Z",
      "neutral_site": true,
      "model_spread": -1.4,
      "game_possessions": 68.1,
      "home_tt": 75.9,
      "away_tt": 74.4,
      "game_total": 150.3,
      "hca": 0,
      "home_bem": 27.53,
      "away_bem": 25.41,
      "home_boe": 123.15,
      "away_boe": 123.78,
      "home_bde": 95.62,
      "away_bde": 98.37,
      "home_bap": 66.3,
      "away_bap": 69.8,
      "home_conf": "B10",
      "away_conf": "ACC",
      "kp_spread": -2.0,
      "kp_total": 152.0,
      "kp_home_score": 77.0,
      "kp_away_score": 75.0,
      "kp_home_wp": 59.0,
      "kp_pred_tempo": 69.0,
      "home_efg": 54.0155,
      "away_efg": 56.6973,
      "home_defg": 48.6133,
      "away_defg": 48.5056,
      "vegas_spread": null,
      "consensus_spread": null,
      "vegas_total": null,
      "spread_book": "",
      "books_count": 0,
      "edge": 0,
      "confidence": "NO_ODDS",
      "recommendation": "NO ODDS",
      "bet_team": "",
      "bet_spread": 0
    }
  ]
}