{
  "generated_at": "2026-03-25 18:20:04",
  "sport": "NHL",
  "model_version": "v2.2",
  "predictions": [
    {
      "away_team": "BOS",
      "home_team": "BUF",
      "away_win_prob": 0.3516,
      "home_win_prob": 0.6484,
      "model_away_odds": 184,
      "model_home_odds": -184,
      "goalie_adj": 0.0,
      "goalie_source": "Both_Indiv",
      "away_goalie": "Joonas Korpisalo",
      "home_goalie": "Alex Lyon",
      "away_b2b": true,
      "home_b2b": false,
      "away_gp": 57,
      "home_gp": 56,
      "away_pre_weight": 0.0,
      "home_pre_weight": 0.0,
      "game_time": "2026-03-25T23:30Z",
      "home_ice_advantage": 0.0386,
      "away_rest_days": 0,
      "home_rest_days": 2,
      "away_3in4": true,
      "home_3in4": false,
      "tz_penalty": 0.0,
      "away_luck_adj": 0.0017,
      "home_luck_adj": 0.0025,
      "rest_effect": 0.07,
      "model_version": "v2.2",
      "vegas_away_odds": 180,
      "vegas_home_odds": -197,
      "away_ev": -0.0155,
      "home_ev": -0.0225,
      "best_bet_team": null,
      "best_bet_odds": null,
      "best_bet_ev": null,
      "kelly_pct": null,
      "recommended_units": null,
      "confidence": "NO_EDGE",
      "recommendation": ""
    },
    {
      "away_team": "NYR",
      "home_team": "TOR",
      "away_win_prob": 0.5547,
      "home_win_prob": 0.4453,
      "model_away_odds": -125,
      "model_home_odds": 125,
      "goalie_adj": 0.0,
      "goalie_source": "Both_Indiv",
      "away_goalie": "Jonathan Quick",
      "home_goalie": "Anthony Stolarz",
      "away_b2b": false,
      "home_b2b": true,
      "away_gp": 56,
      "home_gp": 57,
      "away_pre_weight": 0.0,
      "home_pre_weight": 0.0,
      "game_time": "2026-03-25T23:30Z",
      "home_ice_advantage": 0.0451,
      "away_rest_days": 1,
      "home_rest_days": 0,
      "away_3in4": false,
      "home_3in4": true,
      "tz_penalty": 0.0,
      "away_luck_adj": -0.0035,
      "home_luck_adj": -0.001,
      "rest_effect": -0.06,
      "model_version": "v2.2",
      "vegas_away_odds": -125,
      "vegas_home_odds": 117,
      "away_ev": -0.0015,
      "home_ev": -0.0337,
      "best_bet_team": null,
      "best_bet_odds": null,
      "best_bet_ev": null,
      "kelly_pct": null,
      "recommended_units": null,
      "confidence": "NO_EDGE",
      "recommendation": ""
    }
  ],
  "odds_api_remaining": 316
}